{
"notofangsongkssvertical": {
    "defaults": {
        "ttf": "NotoFangsongKSSVertical-Regular.ttf"
    },
    "distributable": true,
    "family": "Noto Fangsong KSSVertical",
    "familyid": "notofangsongkssvertical",
    "files": {
        "NotoFangsongKSSVertical-Regular.ttf": { "axes": { "wght": 400.0 }, "packagepath": "full/ttf/NotoFangsongKSSVertical-Regular.ttf", "url": "https://github.com/notofonts/notofonts.github.io/raw/main/fonts/NotoFangsongKSSVertical/full/ttf/NotoFangsongKSSVertical-Regular.ttf" }
    },
    "license": "OFL",
    "packageurl": "https://github.com/notofonts/khitan-small-script/releases/download/NotoFangsongKSSVertical-v1.000/NotoFangsongKSSVertical-v1.000.zip",
    "siteurl": "https://github.com/notofonts/khitan-small-script/releases/tag/NotoFangsongKSSVertical-v1.000",
    "source": "Google",
    "status": "current",
    "version": "1.000",
    "ziproot": "NotoFangsongKSSVertical"
}
}